TravSHACL/TravSHACL.py
TravSHACL/__init__.py
TravSHACL/constraints/Constraint.py
TravSHACL/constraints/MaxOnlyConstraint.py
TravSHACL/constraints/MinMaxConstraint.py
TravSHACL/constraints/MinOnlyConstraint.py
TravSHACL/constraints/SPARQLConstraint.py
TravSHACL/constraints/__init__.py
TravSHACL/core/GraphTraversal.py
TravSHACL/core/RulePattern.py
TravSHACL/core/Shape.py
TravSHACL/core/ShapeParser.py
TravSHACL/core/ShapeSchema.py
TravSHACL/core/__init__.py
TravSHACL/rule_based_validation/InstancesRetrieval.py
TravSHACL/rule_based_validation/Validation.py
TravSHACL/rule_based_validation/__init__.py
TravSHACL/sparql/QueryGenerator.py
TravSHACL/sparql/SPARQLEndpoint.py
TravSHACL/sparql/__init__.py
TravSHACL/utils/ValidationStats.py
TravSHACL/utils/VariableGenerator.py
TravSHACL/utils/__init__.py
TravSHACL/utils/fileManagement.py
travshacl-1.9.0.dist-info/licenses/LICENSE
travshacl-1.9.0.dist-info/METADATA
travshacl-1.9.0.dist-info/WHEEL
travshacl-1.9.0.dist-info/top_level.txt
travshacl-1.9.0.dist-info/RECORD
