Metadata-Version: 2.4
Name: TravSHACL
Version: 1.9.0
Summary: A SHACL validator capable of planning the traversal and execution of the validation of a shape schema to detect violations early.
Home-page: https://github.com/SDM-TIB/Trav-SHACL
Download-URL: https://github.com/SDM-TIB/Trav-SHACL/archive/refs/tags/v1.9.0.tar.gz
Author: Mónica Figuera, Philipp D. Rohde
Author-email: philipp.rohde@tib.eu
License: GNU/GPLv3
Project-URL: Documentation, https://sdm-tib.github.io/Trav-SHACL/
Project-URL: Changes, https://sdm-tib.github.io/Trav-SHACL/changelog.html
Project-URL: Source Code, https://github.com/SDM-TIB/Trav-SHACL
Project-URL: Issue Tracker, https://github.com/SDM-TIB/Trav-SHACL/issues
Classifier: Development Status :: 5 - Production/Stable
Classifier: Programming Language :: Python
Classifier: Programming Language :: Python :: 3
Classifier: Programming Language :: Python :: 3 :: Only
Classifier: Programming Language :: Python :: 3.9
Classifier: Programming Language :: Python :: 3.10
Classifier: Programming Language :: Python :: 3.11
Classifier: Programming Language :: Python :: 3.12
Classifier: Programming Language :: Python :: 3.13
Classifier: License :: OSI Approved :: GNU General Public License v3 (GPLv3)
Classifier: Operating System :: OS Independent
Classifier: Intended Audience :: Science/Research
Requires-Python: >=3.8
License-File: LICENSE
Requires-Dist: SPARQLWrapper>=2.0.0
Requires-Dist: rdflib>=6.1.1
Dynamic: author
Dynamic: author-email
Dynamic: classifier
Dynamic: description
Dynamic: description-content-type
Dynamic: download-url
Dynamic: home-page
Dynamic: license
Dynamic: license-file
Dynamic: project-url
Dynamic: requires-dist
Dynamic: requires-python
Dynamic: summary
